{
  "name": "eventstreaming-test",
  "description": "Test digital product event streaming confih",
  "version": "1.0.0",
  "platformVersion": "1.0.0",
  "eventStreamingConfiguration": {
    "topics":
    [
      {
        "name": "test-topic"
      }
    ]
  },
  "components": [
    {
      "name": "producer",
      "description": "Stream producer",
      "controllerType": "deployment",
      "imageName": "softwarefactory.dplt.eu/eventstreaming-test:latest",
      "containerType": "springboot",
      "platformServices": {
        "event-streaming": {
          "applicationType": "kafka"
        }
      }
    }
  ]
}